mm_solana/__init__.py
mm_solana/account.py
mm_solana/balance.py
mm_solana/block.py
mm_solana/py.typed
mm_solana/rpc.py
mm_solana/solana_cli.py
mm_solana/token.py
mm_solana/transfer.py
mm_solana/types.py
mm_solana/utils.py
mm_solana/cli/__init__.py
mm_solana/cli/cli.py
mm_solana/cli/cli_utils.py
mm_solana/cli/cmd/__init__.py
mm_solana/cli/cmd/balance_cmd.py
mm_solana/cli/cmd/balances_cmd.py
mm_solana/cli/cmd/example_cmd.py
mm_solana/cli/cmd/node_cmd.py
mm_solana/cli/cmd/transfer_sol_cmd.py
mm_solana/cli/cmd/wallet/__init__.py
mm_solana/cli/cmd/wallet/keypair_cmd.py
mm_solana/cli/cmd/wallet/new_cmd.py
mm_solana/cli/examples/balances.yml
mm_solana/cli/examples/transfer-sol.yml
mm_solana-0.2.4.dist-info/METADATA
mm_solana-0.2.4.dist-info/WHEEL
mm_solana-0.2.4.dist-info/entry_points.txt
mm_solana-0.2.4.dist-info/RECORD
